django_axor_auth/configurator.py
django_axor_auth/middlewares.py
django_axor_auth/extras/middlewares.py
django_axor_auth/logs/__init__.py
django_axor_auth/logs/admin.py
django_axor_auth/logs/log_response.py
django_axor_auth/logs/managers.py
django_axor_auth/logs/middlewares.py
django_axor_auth/logs/models.py
django_axor_auth/logs/migrations/0001_initial.py
django_axor_auth/logs/migrations/__init__.py
django_axor_auth/security/__init__.py
django_axor_auth/security/encryption.py
django_axor_auth/security/hashing.py
django_axor_auth/static/axor/favicon.svg
django_axor_auth/static/axor/full_logo.svg
django_axor_auth/static/axor/logo.svg
django_axor_auth/static/axor/css/base_template.min.css
django_axor_auth/static/axor/css/form.min.css
django_axor_auth/static/axor/css/main.css
django_axor_auth/static/axor/fonts/Geist.woff2
django_axor_auth/static/axor/js/qrcode.min.js
django_axor_auth/users/__init__.py
django_axor_auth/users/admin.py
django_axor_auth/users/api.py
django_axor_auth/users/managers.py
django_axor_auth/users/middlewares.py
django_axor_auth/users/models.py
django_axor_auth/users/permissions.py
django_axor_auth/users/serializers.py
django_axor_auth/users/urls.py
django_axor_auth/users/views.py
django_axor_auth/users/migrations/0001_initial.py
django_axor_auth/users/migrations/__init__.py
django_axor_auth/users/users_app_tokens/__init__.py
django_axor_auth/users/users_app_tokens/admin.py
django_axor_auth/users/users_app_tokens/api.py
django_axor_auth/users/users_app_tokens/managers.py
django_axor_auth/users/users_app_tokens/models.py
django_axor_auth/users/users_app_tokens/serializers.py
django_axor_auth/users/users_app_tokens/utils.py
django_axor_auth/users/users_app_tokens/migrations/0001_initial.py
django_axor_auth/users/users_app_tokens/migrations/__init__.py
django_axor_auth/users/users_forgot_password/admin.py
django_axor_auth/users/users_forgot_password/managers.py
django_axor_auth/users/users_forgot_password/models.py
django_axor_auth-0.1.6.dist-info/LICENSE
django_axor_auth-0.1.6.dist-info/METADATA
django_axor_auth-0.1.6.dist-info/WHEEL
django_axor_auth-0.1.6.dist-info/top_level.txt
django_axor_auth-0.1.6.dist-info/RECORD
