Metadata-Version: 2.1
Name: django-axor-auth
Version: 0.1.6
Summary: Django authentication API using Django Rest Framework.
Author: Gauravjot Garaya
License: MIT LICENSE
Project-URL: homepage, https://github.com/gauravjot/django-axor-auth
Keywords: django,authentication,rest,api
Classifier: Programming Language :: Python :: 3
Classifier: License :: OSI Approved :: MIT License
Classifier: Operating System :: OS Independent
Requires-Python: >=3.10
License-File: LICENSE
Requires-Dist: pyotp>=2.9.0
Requires-Dist: pyjwt>=2.9.0
Requires-Dist: bcrypt>=4.1.2
Requires-Dist: Django>=5.0
Requires-Dist: djangorestframework>=3.15.0
Requires-Dist: psycopg2-binary>=2.9.9
Requires-Dist: django-cors-headers>=4.3.1
Requires-Dist: pycryptodome>=3.20.0
Requires-Dist: pytz>=2024.1
Requires-Dist: sqlparse>=0.4.4
